git_weblink.py
git_weblink-0.1.dist-info/licenses/LICENSE
git_weblink-0.1.dist-info/METADATA
git_weblink-0.1.dist-info/WHEEL
git_weblink-0.1.dist-info/entry_points.txt
git_weblink-0.1.dist-info/top_level.txt
git_weblink-0.1.dist-info/RECORD
