Metadata-Version: 2.4
Name: git-weblink
Version: 0.1
Summary: Produce web link to a commit, file, or line in a repo
Author-email: Dmitry Gerasimov <di.gerasimov@gmail.com>
License-Expression: MIT
Project-URL: Homepage, https://github.com/dseight/git-weblink
Project-URL: Issues, https://github.com/dseight/git-weblink/issues
Keywords: git
Classifier: Development Status :: 4 - Beta
Classifier: Intended Audience :: Developers
Classifier: Operating System :: OS Independent
Classifier: Programming Language :: Python :: 3
Classifier: Programming Language :: Python :: 3.6
Classifier: Programming Language :: Python :: 3.7
Classifier: Programming Language :: Python :: 3.8
Classifier: Programming Language :: Python :: 3.9
Classifier: Programming Language :: Python :: 3.10
Classifier: Programming Language :: Python :: 3.11
Classifier: Programming Language :: Python :: 3.12
Classifier: Programming Language :: Python :: 3.13
Requires-Python: >=3.6
License-File: LICENSE
Dynamic: license-file
